{
    "type": "FeatureCollection",
    "features": [
        {
            "type": "Feature",
            "properties": {
                "busId": "33045",
                "Azimuth": "221",
                "latitude": -26.03895,
                "longitude": 28.120458,
                "API Response Time": 5.0,
                "Timestamp": "2022-07-30 03:11:40.496377",
                "GPSLastupdatedDate": "2022-07-30 ",
                "GPSLastupdatedTime": "01:11"
            },
            "geometry": {
                "type": "Point",
                "coordinates": [
                    28.120458,
                    -26.03895
                ]
            }
        },
        {
            "type": "Feature",
            "properties": {
                "busId": "33012",
                "Azimuth": "12",
                "latitude": -26.038905,
                "longitude": 28.12062,
                "API Response Time": 5.0,
                "Timestamp": "2022-07-30 03:11:40.496430",
                "GPSLastupdatedDate": "2022-07-30 ",
                "GPSLastupdatedTime": "01:11"
            },
            "geometry": {
                "type": "Point",
                "coordinates": [
                    28.12062,
                    -26.038905
                ]
            }
        },
        {
            "type": "Feature",
            "properties": {
                "busId": "33009",
                "Azimuth": "217",
                "latitude": -26.038887,
                "longitude": 28.12035,
                "API Response Time": 5.0,
                "Timestamp": "2022-07-30 03:11:40.496449",
                "GPSLastupdatedDate": "2022-07-30 ",
                "GPSLastupdatedTime": "01:11"
            },
            "geometry": {
                "type": "Point",
                "coordinates": [
                    28.12035,
                    -26.038887
                ]
            }
        },
        {
            "type": "Feature",
            "properties": {
                "busId": "32992",
                "Azimuth": "245",
                "latitude": -26.039222,
                "longitude": 28.120127,
                "API Response Time": 5.0,
                "Timestamp": "2022-07-30 03:11:40.496465",
                "GPSLastupdatedDate": "2022-07-30 ",
                "GPSLastupdatedTime": "01:11"
            },
            "geometry": {
                "type": "Point",
                "coordinates": [
                    28.120127,
                    -26.039222
                ]
            }
        },
        {
            "type": "Feature",
            "properties": {
                "busId": "33039",
                "Azimuth": "219",
                "latitude": -26.039118,
                "longitude": 28.120008,
                "API Response Time": 5.0,
                "Timestamp": "2022-07-30 03:11:40.496479",
                "GPSLastupdatedDate": "2022-07-30 ",
                "GPSLastupdatedTime": "01:11"
            },
            "geometry": {
                "type": "Point",
                "coordinates": [
                    28.120008,
                    -26.039118
                ]
            }
        },
        {
            "type": "Feature",
            "properties": {
                "busId": "31595",
                "Azimuth": "232",
                "latitude": -26.039383,
                "longitude": 28.12015,
                "API Response Time": 5.0,
                "Timestamp": "2022-07-30 03:11:40.496495",
                "GPSLastupdatedDate": "2022-07-30 ",
                "GPSLastupdatedTime": "01:11"
            },
            "geometry": {
                "type": "Point",
                "coordinates": [
                    28.12015,
                    -26.039383
                ]
            }
        },
        {
            "type": "Feature",
            "properties": {
                "busId": "31945",
                "Azimuth": "214",
                "latitude": -26.039343,
                "longitude": 28.120127,
                "API Response Time": 5.0,
                "Timestamp": "2022-07-30 03:11:40.496509",
                "GPSLastupdatedDate": "2022-07-30 ",
                "GPSLastupdatedTime": "01:11"
            },
            "geometry": {
                "type": "Point",
                "coordinates": [
                    28.120127,
                    -26.039343
                ]
            }
        },
        {
            "type": "Feature",
            "properties": {
                "busId": "31597",
                "Azimuth": "220",
                "latitude": -26.03951,
                "longitude": 28.120068,
                "API Response Time": 5.0,
                "Timestamp": "2022-07-30 03:11:40.496524",
                "GPSLastupdatedDate": "2022-07-30 ",
                "GPSLastupdatedTime": "01:11"
            },
            "geometry": {
                "type": "Point",
                "coordinates": [
                    28.120068,
                    -26.03951
                ]
            }
        },
        {
            "type": "Feature",
            "properties": {
                "busId": "32994",
                "Azimuth": "225",
                "latitude": -26.038725,
                "longitude": 28.120348,
                "API Response Time": 5.0,
                "Timestamp": "2022-07-30 03:11:40.496538",
                "GPSLastupdatedDate": "2022-07-30 ",
                "GPSLastupdatedTime": "01:11"
            },
            "geometry": {
                "type": "Point",
                "coordinates": [
                    28.120348,
                    -26.038725
                ]
            }
        },
        {
            "type": "Feature",
            "properties": {
                "busId": "33030",
                "Azimuth": "353",
                "latitude": -26.039078,
                "longitude": 28.120187,
                "API Response Time": 5.0,
                "Timestamp": "2022-07-30 03:11:40.496553",
                "GPSLastupdatedDate": "2022-07-30 ",
                "GPSLastupdatedTime": "01:11"
            },
            "geometry": {
                "type": "Point",
                "coordinates": [
                    28.120187,
                    -26.039078
                ]
            }
        },
        {
            "type": "Feature",
            "properties": {
                "busId": "33027",
                "Azimuth": "226",
                "latitude": -26.03929,
                "longitude": 28.120203,
                "API Response Time": 5.0,
                "Timestamp": "2022-07-30 03:11:40.496567",
                "GPSLastupdatedDate": "2022-07-30 ",
                "GPSLastupdatedTime": "01:11"
            },
            "geometry": {
                "type": "Point",
                "coordinates": [
                    28.120203,
                    -26.03929
                ]
            }
        },
        {
            "type": "Feature",
            "properties": {
                "busId": "31951",
                "Azimuth": "214",
                "latitude": -26.03882,
                "longitude": 28.120248,
                "API Response Time": 5.0,
                "Timestamp": "2022-07-30 03:11:40.496581",
                "GPSLastupdatedDate": "2022-07-30 ",
                "GPSLastupdatedTime": "01:11"
            },
            "geometry": {
                "type": "Point",
                "coordinates": [
                    28.120248,
                    -26.03882
                ]
            }
        },
        {
            "type": "Feature",
            "properties": {
                "busId": "31947",
                "Azimuth": "215",
                "latitude": -26.039422,
                "longitude": 28.119973,
                "API Response Time": 5.0,
                "Timestamp": "2022-07-30 03:11:40.496595",
                "GPSLastupdatedDate": "2022-07-30 ",
                "GPSLastupdatedTime": "01:11"
            },
            "geometry": {
                "type": "Point",
                "coordinates": [
                    28.119973,
                    -26.039422
                ]
            }
        },
        {
            "type": "Feature",
            "properties": {
                "busId": "33010",
                "Azimuth": "6",
                "latitude": -26.03906,
                "longitude": 28.120328,
                "API Response Time": 5.0,
                "Timestamp": "2022-07-30 03:11:40.496609",
                "GPSLastupdatedDate": "2022-07-30 ",
                "GPSLastupdatedTime": "01:11"
            },
            "geometry": {
                "type": "Point",
                "coordinates": [
                    28.120328,
                    -26.03906
                ]
            }
        },
        {
            "type": "Feature",
            "properties": {
                "busId": "31955",
                "Azimuth": "242",
                "latitude": -26.038833,
                "longitude": 28.120535,
                "API Response Time": 5.0,
                "Timestamp": "2022-07-30 03:11:40.496624",
                "GPSLastupdatedDate": "2022-07-30 ",
                "GPSLastupdatedTime": "01:11"
            },
            "geometry": {
                "type": "Point",
                "coordinates": [
                    28.120535,
                    -26.038833
                ]
            }
        },
        {
            "type": "Feature",
            "properties": {
                "busId": "33004",
                "Azimuth": "218",
                "latitude": -26.038892,
                "longitude": 28.120582,
                "API Response Time": 5.0,
                "Timestamp": "2022-07-30 03:11:40.496638",
                "GPSLastupdatedDate": "2022-07-30 ",
                "GPSLastupdatedTime": "01:11"
            },
            "geometry": {
                "type": "Point",
                "coordinates": [
                    28.120582,
                    -26.038892
                ]
            }
        },
        {
            "type": "Feature",
            "properties": {
                "busId": "33047",
                "Azimuth": "219",
                "latitude": -26.039003,
                "longitude": 28.120473,
                "API Response Time": 5.0,
                "Timestamp": "2022-07-30 03:11:40.496652",
                "GPSLastupdatedDate": "2022-07-30 ",
                "GPSLastupdatedTime": "01:11"
            },
            "geometry": {
                "type": "Point",
                "coordinates": [
                    28.120473,
                    -26.039003
                ]
            }
        },
        {
            "type": "Feature",
            "properties": {
                "busId": "32993",
                "Azimuth": "206",
                "latitude": -26.039065,
                "longitude": 28.12041,
                "API Response Time": 5.0,
                "Timestamp": "2022-07-30 03:11:40.496667",
                "GPSLastupdatedDate": "2022-07-30 ",
                "GPSLastupdatedTime": "01:11"
            },
            "geometry": {
                "type": "Point",
                "coordinates": [
                    28.12041,
                    -26.039065
                ]
            }
        },
        {
            "type": "Feature",
            "properties": {
                "busId": "33002",
                "Azimuth": "265",
                "latitude": -26.037613,
                "longitude": 28.120988,
                "API Response Time": 5.0,
                "Timestamp": "2022-07-30 03:11:40.496681",
                "GPSLastupdatedDate": "2022-07-30 ",
                "GPSLastupdatedTime": "01:11"
            },
            "geometry": {
                "type": "Point",
                "coordinates": [
                    28.120988,
                    -26.037613
                ]
            }
        },
        {
            "type": "Feature",
            "properties": {
                "busId": "31956",
                "Azimuth": "211",
                "latitude": -26.038723,
                "longitude": 28.120665,
                "API Response Time": 5.0,
                "Timestamp": "2022-07-30 03:11:40.496695",
                "GPSLastupdatedDate": "2022-07-30 ",
                "GPSLastupdatedTime": "01:11"
            },
            "geometry": {
                "type": "Point",
                "coordinates": [
                    28.120665,
                    -26.038723
                ]
            }
        },
        {
            "type": "Feature",
            "properties": {
                "busId": "31952",
                "Azimuth": "216",
                "latitude": -26.038822,
                "longitude": 28.120505,
                "API Response Time": 5.0,
                "Timestamp": "2022-07-30 03:11:40.496710",
                "GPSLastupdatedDate": "2022-07-30 ",
                "GPSLastupdatedTime": "01:11"
            },
            "geometry": {
                "type": "Point",
                "coordinates": [
                    28.120505,
                    -26.038822
                ]
            }
        },
        {
            "type": "Feature",
            "properties": {
                "busId": "31946",
                "Azimuth": "219",
                "latitude": -26.039143,
                "longitude": 28.120245,
                "API Response Time": 5.0,
                "Timestamp": "2022-07-30 03:11:40.496725",
                "GPSLastupdatedDate": "2022-07-30 ",
                "GPSLastupdatedTime": "01:11"
            },
            "geometry": {
                "type": "Point",
                "coordinates": [
                    28.120245,
                    -26.039143
                ]
            }
        }
    ]
}